FusionVet-1.0.1.data/scripts/FusionVet.py
vetmodule/AberrantRead.py
vetmodule/BamToBed.py
vetmodule/GetBamFiles.py
vetmodule/Overlap.py
vetmodule/ReadFusion.py
vetmodule/__init__.py
vetmodule/bam_cigar.py
FusionVet-1.0.1.dist-info/LICENSE.txt
FusionVet-1.0.1.dist-info/METADATA
FusionVet-1.0.1.dist-info/WHEEL
FusionVet-1.0.1.dist-info/top_level.txt
FusionVet-1.0.1.dist-info/RECORD
