Metadata-Version: 2.1
Name: FusionVet
Version: 1.0.1
Summary: A bioinformatics tool to visualize and evaluate *known* gene fusions
Home-page: https://fusionvet.readthedocs.io/en/latest/index.html
Author: Liguo Wang
Author-email: wangliguo78@gmail.com
License: UNKNOWN
Keywords: gene fusion,validation,visualization,UCSC,BAM,bed,bigBed,interact,bigInteract
Platform: Linux
Platform: MacOS
Classifier: Development Status :: 5 - Production/Stable
Classifier: Environment :: Console
Classifier: Intended Audience :: Science/Research
Classifier: License :: OSI Approved :: GNU General Public License v2 (GPLv2)
Classifier: Operating System :: MacOS :: MacOS X
Classifier: Operating System :: POSIX
Classifier: Programming Language :: Python
Classifier: Topic :: Scientific/Engineering :: Bio-Informatics
Requires-Python: >=3.5
Requires-Dist: numpy
Requires-Dist: scipy
Requires-Dist: pysam
